Metadata-Version: 1.1
Name: gcsavoidinfiniteretries
Version: 0.0.2
Summary: Avoid infinite retries Python package
Home-page: UNKNOWN
Author: Omar Fateh
Author-email: fatehomar0@gmail.com
License: UNKNOWN
Keywords: python,Google Cloud
Platform: UNKNOWN
Classifier: Development Status :: 3 - Alpha
Classifier: Intended Audience :: Education
Classifier: Programming Language :: Python :: 2
Classifier: Programming Language :: Python :: 3
Classifier: Operating System :: MacOS :: MacOS X
Classifier: Operating System :: Microsoft :: Windows
